notebooks/__init__.py
notebooks/tests/__init__.py
notebooks/tests/test_fermi_hubbard_notebooks.py
notebooks/tests/test_first_quantized_notebook.py
notebooks/tests/test_scheduler_notebook.py
pyLIQTR/__init__.py
pyLIQTR/_version.py
pyLIQTR/BlockEncodings/BlockEncoding.py
pyLIQTR/BlockEncodings/CarlemanLinearization.py
pyLIQTR/BlockEncodings/DoubleFactorized.py
pyLIQTR/BlockEncodings/FirstQuantized.py
pyLIQTR/BlockEncodings/LinearT.py
pyLIQTR/BlockEncodings/PauliStringLCU.py
pyLIQTR/BlockEncodings/__init__.py
pyLIQTR/BlockEncodings/fermi_hubbard_square_encoding.py
pyLIQTR/BlockEncodings/getEncoding.py
pyLIQTR/PhaseEstimation/__init__.py
pyLIQTR/PhaseEstimation/pe.py
pyLIQTR/PhaseEstimation/pe_gates.py
pyLIQTR/PhaseEstimation/pe_sim.py
pyLIQTR/PhaseEstimation/tests/__init__.py
pyLIQTR/PhaseEstimation/tests/test_pe_gates.py
pyLIQTR/ProblemInstances/ChemicalHamiltonian.py
pyLIQTR/ProblemInstances/ElectronicStructure.py
pyLIQTR/ProblemInstances/LatticeInstance.py
pyLIQTR/ProblemInstances/MatrixInstance.py
pyLIQTR/ProblemInstances/MoleculeParameters.py
pyLIQTR/ProblemInstances/NonlinearODE.py
pyLIQTR/ProblemInstances/ProblemInstance.py
pyLIQTR/ProblemInstances/__init__.py
pyLIQTR/ProblemInstances/fermionic_models.py
pyLIQTR/ProblemInstances/getInstance.py
pyLIQTR/ProblemInstances/spin_models.py
pyLIQTR/circuits/__init__.py
pyLIQTR/circuits/pyLCircuit.py
pyLIQTR/circuits/pyLOperator.py
pyLIQTR/circuits/qsp.py
pyLIQTR/circuits/operators/AddIntoPhaseGrad.py
pyLIQTR/circuits/operators/AddMod.py
pyLIQTR/circuits/operators/ApplyNuclearPhase.py
pyLIQTR/circuits/operators/BinaryToUnary.py
pyLIQTR/circuits/operators/BitwiseZRotation.py
pyLIQTR/circuits/operators/CatalyticallyControlledHadamard.py
pyLIQTR/circuits/operators/ControlledAddOrSubtract.py
pyLIQTR/circuits/operators/ControlledCopy.py
pyLIQTR/circuits/operators/ControlledUniformSuperposition.py
pyLIQTR/circuits/operators/DF_InnerPrepare.py
pyLIQTR/circuits/operators/DF_OuterPrepare.py
pyliqtr-1.4.2.dist-info/licenses/LICENSE.txt
pyliqtr-1.4.2.dist-info/METADATA
pyliqtr-1.4.2.dist-info/WHEEL
pyliqtr-1.4.2.dist-info/top_level.txt
pyliqtr-1.4.2.dist-info/RECORD
