Metadata-Version: 2.4
Name: pyLIQTR
Version: 1.4.2
Summary: A python package for generating quantum circuits using quantum algorithms.
Author: Kevin Obenland, Justin Elenewski, Kaitlyn Morrell, Rylee Stuart Neumann, Arthur Kurlej, Robert Rood, John Blue, Joe Belarge, Benjamin Rempfer & Parker Kuklinski
Author-email: Kevin.Obenland@ll.mit.edu
License: BDS-2
Requires-Python: >=3.8,<=3.12.2
License-File: LICENSE.txt
Requires-Dist: cirq-core
Requires-Dist: qualtran==0.4.0
Requires-Dist: ipykernel
Requires-Dist: numpy
Requires-Dist: pandas
Requires-Dist: scipy
Requires-Dist: matplotlib
Requires-Dist: tqdm
Requires-Dist: openfermion
Requires-Dist: portalocker
Requires-Dist: ply
Requires-Dist: gmpy2
Requires-Dist: networkx
Requires-Dist: juliacall
Requires-Dist: juliapkg
Requires-Dist: rustworkx
Requires-Dist: pydot
Requires-Dist: graphviz
Requires-Dist: openfermionpyscf; sys_platform == "linux"
Provides-Extra: dev
Requires-Dist: ipykernel; extra == "dev"
Requires-Dist: ipython; extra == "dev"
Requires-Dist: jupyter; extra == "dev"
Requires-Dist: jupyterlab; extra == "dev"
Requires-Dist: black; extra == "dev"
Requires-Dist: mypy; extra == "dev"
Requires-Dist: pylint; extra == "dev"
Requires-Dist: pytest; extra == "dev"
Requires-Dist: pytest-cov; extra == "dev"
Requires-Dist: pytest-pep8; extra == "dev"
Requires-Dist: testbook; extra == "dev"
Requires-Dist: nbsphinx; extra == "dev"
Requires-Dist: pypandoc; extra == "dev"
Requires-Dist: recommonmark; extra == "dev"
Requires-Dist: Sphinx; extra == "dev"
Requires-Dist: sphinx_rtd_theme; extra == "dev"
Requires-Dist: myst-parser; extra == "dev"
Requires-Dist: myst_nb; extra == "dev"
Requires-Dist: jupyter_sphinx; extra == "dev"
Requires-Dist: jupytext; extra == "dev"
Dynamic: author
Dynamic: author-email
Dynamic: description
Dynamic: description-content-type
Dynamic: license
Dynamic: license-file
Dynamic: provides-extra
Dynamic: requires-dist
Dynamic: requires-python
Dynamic: summary
